MASlite-2023.1.1.data/data/license.md
MASlite-2023.1.1.data/data/readme.md
maslite/__init__.py
maslite/version.py
MASlite-2023.1.1.dist-info/METADATA
MASlite-2023.1.1.dist-info/WHEEL
MASlite-2023.1.1.dist-info/top_level.txt
MASlite-2023.1.1.dist-info/RECORD
