Metadata-Version: 2.1
Name: MASlite
Version: 2023.1.1
Summary: A fast & lightweight multi-agent system kernel
Home-page: https://github.com/root-11/maslite
Author: root-11
License: MIT
Keywords: multi agent system,MAS,maslite
Platform: any
Classifier: Development Status :: 5 - Production/Stable
Classifier: Intended Audience :: Science/Research
Classifier: Natural Language :: English
Classifier: License :: OSI Approved :: MIT License
Classifier: Programming Language :: Python :: 3.8
Classifier: Programming Language :: Python :: 3.9
Classifier: Programming Language :: Python :: 3.10
Classifier: Programming Language :: Python :: 3.11
